fudataqa/__init__.py
fudataqa/tensorflow/__init__.py
fudataqa/tensorflow/core/__init__.py
fudataqa/tensorflow/core/framework/__init__.py
fudataqa/tensorflow/core/framework/allocation_description_pb2.py
fudataqa/tensorflow/core/framework/allocation_description_pb2_grpc.py
fudataqa/tensorflow/core/framework/api_def_pb2.py
fudataqa/tensorflow/core/framework/api_def_pb2_grpc.py
fudataqa/tensorflow/core/framework/attr_value_pb2.py
fudataqa/tensorflow/core/framework/attr_value_pb2_grpc.py
fudataqa/tensorflow/core/framework/cost_graph_pb2.py
fudataqa/tensorflow/core/framework/cost_graph_pb2_grpc.py
fudataqa/tensorflow/core/framework/device_attributes_pb2.py
fudataqa/tensorflow/core/framework/device_attributes_pb2_grpc.py
fudataqa/tensorflow/core/framework/function_pb2.py
fudataqa/tensorflow/core/framework/function_pb2_grpc.py
fudataqa/tensorflow/core/framework/graph_pb2.py
fudataqa/tensorflow/core/framework/graph_pb2_grpc.py
fudataqa/tensorflow/core/framework/graph_transfer_info_pb2.py
fudataqa/tensorflow/core/framework/graph_transfer_info_pb2_grpc.py
fudataqa/tensorflow/core/framework/kernel_def_pb2.py
fudataqa/tensorflow/core/framework/kernel_def_pb2_grpc.py
fudataqa/tensorflow/core/framework/log_memory_pb2.py
fudataqa/tensorflow/core/framework/log_memory_pb2_grpc.py
fudataqa/tensorflow/core/framework/node_def_pb2.py
fudataqa/tensorflow/core/framework/node_def_pb2_grpc.py
fudataqa/tensorflow/core/framework/op_def_pb2.py
fudataqa/tensorflow/core/framework/op_def_pb2_grpc.py
fudataqa/tensorflow/core/framework/reader_base_pb2.py
fudataqa/tensorflow/core/framework/reader_base_pb2_grpc.py
fudataqa/tensorflow/core/framework/remote_fused_graph_execute_info_pb2.py
fudataqa/tensorflow/core/framework/remote_fused_graph_execute_info_pb2_grpc.py
fudataqa/tensorflow/core/framework/resource_handle_pb2.py
fudataqa/tensorflow/core/framework/resource_handle_pb2_grpc.py
fudataqa/tensorflow/core/framework/step_stats_pb2.py
fudataqa/tensorflow/core/framework/step_stats_pb2_grpc.py
fudataqa-1.0.dist-info/METADATA
fudataqa-1.0.dist-info/WHEEL
fudataqa-1.0.dist-info/top_level.txt
fudataqa-1.0.dist-info/RECORD
