Metadata-Version: 2.1
Name: fudataqa
Version: 1.0
Summary: My First PyPI
Home-page: http://www.baidu.com
Author: youlong
Author-email: youlong@fudata.cn
License: UNKNOWN
Platform: UNKNOWN
